RISC_Processor/multi_cycle.v
// Ansh Shah (2018A3PS0294P)
// Abhinandan Sharma (2018A3PS0095P)
// Tanvi Shewale (2018A3PS0298P)


//*********************************************************************************************************************************************************
//testbench
`timescale 1ns/1ps 
module tb_multi_cycle ();
reg clk, rst;
reg [15:0] PC_init;

wire error_log_1, error_log_2, error_log_3;

//Control signals
wire IR_write, PC_write_cond, PC_write, mem_read, mem_write, mem_to_reg, reg_write;
wire [1:0] PC_src;
wire [2:0] ALU_src_A, ALU_src_B;
wire [15:0] PC;
wire [3:0] stage;

parameter T = 10;

multi_cycle uut (rst, PC_init, clk, error_log_1, error_log_2, error_log_3,
	IR_write, PC_write_cond, PC_write, mem_read, mem_write, mem_to_reg, reg_write,
	PC_src, ALU_src_A, ALU_src_B, PC, stage);

initial
begin
	clk = 1'b0;
	#(T/2)
	forever #(T/2) clk = ~clk;
end

always@(posedge error_log_1)
begin
	$display ("ERROR_1 : Contents of R0 cannot be modified");
	$finish;
end

always@(posedge error_log_2)
begin
	$display ("ERROR_2 : Invalid function field for shift operation");
	$finish;
end

always@(posedge error_log_3)
begin
	$display ("ERROR_3 : Cannot branch/ jump to an odd address in instruction memory");
	$finish;
end

initial
begin
	forever
	begin
		#(T)
		$display ($time);
		$display ("stage			=		%d", stage);	//Refer the control unit FSM to determine the stage (IF, ID, EX, MEM, WB)
		$display ("PC			=		%hH", PC);
		$display ("PC_write		=		%b", PC_write);
		$display ("IR_write		=		%b", IR_write);
		$display ("ALU_src_A		=		%b", ALU_src_A);
		$display ("ALU_src_B		=		%b", ALU_src_B);
		$display ("PC_src			=		%b", PC_src);
		$display ("reg_write		=		%b", reg_write);
		$display ("PC_write_cond		=		%b", PC_write_cond);
		$display ("mem_to_reg		=		%b", mem_to_reg);
		$display ("mem_read		=		%b", mem_read);
		$display ("mem_write		=		%b", mem_write);
		$display ("");
	end
end

initial
begin
	$dumpfile("multi_cycle.vcd");
	$dumpvars(0, tb_multi_cycle);

	rst = 1'b1;			
	PC_init = 16'd0;	// Change this to the address from where the fetching needs to be started
	#(T/4)
	rst = 1'b0;
	#(159*T) $finish;	// Change this based on the time the instructions will require to get executed
end
	
endmodule
	

//****************************************************************************************************************************************************

module multi_cycle (rst, PC_init, clk, error_log_1, error_log_2, error_log_3,
		IR_write, PC_write_cond, PC_write, mem_read, mem_write, mem_to_reg, reg_write,
		PC_src, ALU_src_A, ALU_src_B, PC, stage);
		
input clk, rst;
input [15:0] PC_init;
output error_log_1, error_log_2, error_log_3;

//Control signals
output reg IR_write, PC_write_cond, PC_write, mem_read, mem_write, mem_to_reg, reg_write;
output reg [1:0] PC_src;
output reg [2:0] ALU_src_A, ALU_src_B;
output [15:0] PC;

//Stage counter
output [3:0] stage;

reg [3:0] stage = 4'd0;
reg PC = 16'd0;

//error log
reg error_log_1 = 1'b0;	// error due to write back in R0
reg error_log_2 = 1'b0;	// error due to invalid function field in case of shift instruction
reg error_log_3 = 1'b0;	// error if an attempt is made to branch/ jump to an odd address in ins_mem

//Storage instantiation
reg [7:0] ins_mem [0 : ((2**16) - 1)];
reg [7:0] data_mem [0 : ((2**16) - 1)];
//reg [7:0] ins_mem [0 : 127];		// May use this memory initialization for faster simulation
//reg [7:0] data_mem [0 : 127];		// May use this memory initialization for faster simulation

//PC, Instruction memory and Instruction register i/o
reg [15:0] IR, instr;

//ALU i/o
reg [15:0] ALU_out, ALU_result;
reg zero;
reg [2:0] ALU_ctrl;
reg [15:0] temp1;
reg [15:0] temp2;

//Data memory i/o
reg [15:0] write_data, read_addr, write_addr, MDR;

//Register file i/o
reg [15:0] A, B, C, wd;
reg [3:0] rdr1,rdr2,rdr3,wrr;
reg [15:0] reg_file [0:15];

//Mux outputs
reg [3:0] mux11, mux12, mux13;
reg  mux3; 
reg [15:0] mux21, mux22, mux4, mux5;


//*************************************************************************************************

//Load Register File 
initial                                        
	$readmemh("reg_file.dat",reg_file);

//Load data memory File 
initial
	$readmemh("data_mem.dat",data_mem);

//Load instruction memory File 
initial
	$readmemh("ins_mem.dat",ins_mem);

//*************************************************************************************************

//PC
always@(posedge clk, posedge rst)
begin
	if (rst)
	begin
		PC = PC_init;
		reg_file[0] = 16'd0;
		reg_file[1] = 16'd0;
		reg_file[2] = 16'd0;
		reg_file[3] = 16'd0;
		reg_file[4] = 16'd0;
		reg_file[5] = 16'd0;
		reg_file[6] = 16'd0;
		reg_file[7] = 16'd0;
		reg_file[8] = 16'd0;
		reg_file[9] = 16'd0;
		reg_file[10] = 16'd0;
		reg_file[11] = 16'd0;
		reg_file[12] = 16'd0;
		reg_file[13] = 16'd0;
		reg_file[14] = 16'd0;
		reg_file[15] = 16'd0;
	end	
		
	else if ((mux3 & PC_write_cond) | PC_write)
		PC = mux4;
end

// error_log_3
always@(*)
begin
	if ((PC % 2) == 1'b1)	// odd address found
		error_log_3 = 1'b1;
end
	
//Instruction Memory
always@(*)
begin
	instr = {ins_mem[PC+1], ins_mem[PC]};	//Little Endian
end

//Instruction Register
always@(*)
begin
	if (IR_write)
	begin
		IR = instr;
	end
end

//Mux11, Mux12
always@(*)
begin
	if ((IR[15:12] == 4'b0001) | (IR[15:12] == 4'b0010))
	begin	//reg_src1 = 1 and reg_src2 = 1 and reg_wrr = 1 
		mux11 = {2'b10, IR[9:8]};
		mux12 = {2'b11, IR[11:10]};
		mux13 = {2'b11, IR[11:10]};
	end
	
	else	//reg_src1 = 0 and reg_src2 = 0 and reg_wrr = 0												
	begin
		mux11 = IR[7:4];
		mux12 = IR[3:0];
		mux13 = IR[11:8];
	end
end

//Register File
always@(posedge clk)
begin
	rdr1 = mux11;
	rdr2 = mux12;
	rdr3 = IR[11:8];
	wrr  = mux13;
	
	A = reg_file[rdr1];
	B = reg_file[rdr2];
	C = reg_file[rdr3];
	
	if (reg_write)
	begin
		wd = mux5;
		if (wrr != 4'd0)
		begin
			reg_file[wrr] = wd;
			$writememh("reg_file.dat",reg_file);
		end
		
		else
			error_log_1 = 1'b1;
	end
end

//Mux21
always@(*)
begin
	case(ALU_src_A)
		3'b000	:	mux21 = PC;
		3'b001	:	mux21 = A;
		3'b010	:	mux21 = {{8{IR[7]}}, IR[7:0]};
		3'b011	:	mux21 = {8'd0, IR[7:0]};
		3'b100	:	mux21 = {12'd0, IR[7:4]};
		default	:	mux21 = 16'bx;
	endcase
end

//Mux22
always@(*)
begin
	case(ALU_src_B)
		3'b000	:	mux22 = 16'd2;
		3'b001	:	mux22 = B;
		3'b010	:	mux22 = C;
		3'b011	:	mux22 = {{7{IR[7]}}, IR[7:0], 1'b0};
		3'b100	:	mux22 = {{4{IR[11]}}, IR[11:0]};
		default	:	mux22 = 16'bx;
	endcase
end

//ALU
always@(*)
begin
	temp1 = mux21;
	temp2 = mux22;
	case(ALU_ctrl)
		3'b000	:	ALU_result = mux21 + mux22;
		
		3'b001	: 	begin
						case(IR[15:12] )
							4'b1100	:	begin	//SUB reg
											if (mux21 > mux22)
												ALU_result = mux21 - mux22;
									
											else
											begin
												ALU_result = mux22 - mux21;
												ALU_result = ~(ALU_result) + 16'd1;
											end	
										end
										
							4'b0100	:	ALU_result = mux21 - mux22;		//BE								
							4'b0101	:	ALU_result = mux21 - mux22;		//BNE
							
							4'b1110	:	begin	//SUB imm zero
											if (mux22 > mux21)
												ALU_result = mux22 - mux21;
									
											else
											begin
												ALU_result = mux21 - mux22;
												ALU_result = ~(ALU_result) + 16'd1;
											end	
										end
							4'b1101	:	begin	//SUB imm MSB
											if (mux22 > mux21)
												ALU_result = mux22 - mux21;
									
											else
											begin
												ALU_result = mux21 - mux22;
												ALU_result = ~(ALU_result) + 16'd1;
											end	
										end
							default	:	ALU_result = 16'bx;
						endcase
					end
					
		3'b010	: 	ALU_result = ~(mux21 & mux22);
		3'b011	: 	ALU_result = mux21 | mux22;
		3'b100	: 	begin
						while (temp1 > 0)
						begin
							temp2 = {temp2[14:0],1'b0};
							temp1 = temp1 - 16'd1;
						end
						ALU_result = temp2;
					end
		3'b101	:	begin
						while (temp1 > 0)
						begin
							temp2 = {1'b0,temp2[15:1]};
							temp1 = temp1 - 16'd1;
						end
						ALU_result = temp2;
					end
		3'b110	: 	begin
						while (temp1 > 0)
						begin
							temp2 = {temp2[15],temp2[15:1]};
							temp1 = temp1 - 16'd1;
						end
						ALU_result = temp2;
					end
		default	:	ALU_result = 16'bx;
	endcase
	zero = (ALU_result == 16'd0) ? 1'b1 : 1'b0;
end

//ALU Control
always @(*)
begin
	/*
	add:    000
	sub:    001
	nand:   010
	or:     011
	shift:  100 (left)
	shift:  101 (right logical)
	shift:  110 (right MSB)
	*/
	
	case (stage)		
		4'b0000	:	ALU_ctrl = 3'b000; // PC+2
		4'b0001	:	ALU_ctrl = 3'b000; // JMP address
		
		4'b0010	:	begin
						case(IR[15:12]) //opcode = IR[15:12]
							4'b1000	:	ALU_ctrl = 3'b000;	//ADD reg
							4'b1100	:	ALU_ctrl = 3'b001;	//SUB reg
							4'b1011	:	ALU_ctrl = 3'b010;	//NAND reg
							4'b1111	:	ALU_ctrl = 3'b011;	//OR reg
							default	:	ALU_ctrl = 3'bxxx;
						endcase
					end
					
		4'b0011	: 	begin 	//shift
						case(IR[3:0])	//func_field = IR[3:0]
							4'b0001:  	ALU_ctrl = 3'b100; // shift left
							4'b0010:  	ALU_ctrl = 3'b101; // shift right logical
							4'b0011:  	ALU_ctrl = 3'b110; // shift right copy MSB
							default:	begin
											ALU_ctrl = 3'bxxx;
											error_log_2 = 1'b1;
										end
						endcase	
					end
					
		4'b0100	: 	begin
						case(IR[15:12])
							4'b1010	:	ALU_ctrl = 3'b000;	//ADD Imm zero
							4'b1110	:	ALU_ctrl = 3'b001;	//SUB Imm zero
							default	:	ALU_ctrl = 3'bxxx;
						endcase
					end
					
		4'b0101	: 	begin
						case(IR[15:12])
							4'b1001	:	ALU_ctrl = 3'b000;	//ADD imm MSB
							4'b1101	:	ALU_ctrl = 3'b001;	//SUB imm MSB
							4'b0111	:	ALU_ctrl = 3'b010;	//NAND imm MSB
							4'b0110	:	ALU_ctrl = 3'b011;	//OR imm MSB
							default	:	ALU_ctrl = 3'bxxx;
						endcase
					end
					
		4'b0110	: 	ALU_ctrl = 3'b000; // PC update for JMP
		4'b0111	: 	ALU_ctrl = 3'b000; // LOAD / STORE		
 		4'b1000	: 	ALU_ctrl = 3'b001; // BE / BNE
		
		4'b1001	: 	begin
						case(IR[15:12]) //opcode = IR[15:12]
							4'b1000	:	ALU_ctrl = 3'b000;	//ADD reg
							4'b1100	:	ALU_ctrl = 3'b001;	//SUB reg
							4'b1011	:	ALU_ctrl = 3'b010;	//NAND reg
							4'b1111	:	ALU_ctrl = 3'b011;	//OR reg
							4'b0000	:	begin 	//shift
											case(IR[3:0])	//func_field = IR[3:0]
												4'b0001:  ALU_ctrl = 3'b100; // shift left
												4'b0010:  ALU_ctrl = 3'b101; // shift right logical
												4'b0011:  ALU_ctrl = 3'b110; // shift right copy MSB
												default: ALU_ctrl = 3'bxxx;
											endcase
										end
							4'b1010	:	ALU_ctrl = 3'b000;	//ADD Imm zero
							4'b1110	:	ALU_ctrl = 3'b001;	//SUB Imm zero
							4'b1001	:	ALU_ctrl = 3'b000;	//ADD imm MSB
							4'b1101	:	ALU_ctrl = 3'b001;	//SUB imm MSB
							4'b0111	:	ALU_ctrl = 3'b010;	//NAND imm MSB
							4'b0110	:	ALU_ctrl = 3'b011;	//OR imm MSB
							default	:	ALU_ctrl = 3'bxxx;
						endcase
					end
					
		4'b1010	: 	ALU_ctrl = 3'b000; // LOAD
		4'b1011	: 	ALU_ctrl = 3'b000; // STORE
		4'b1100	: 	ALU_ctrl = 3'b000; // Maintain LOAD
 		default	: 	ALU_ctrl = 3'bxxx;
	endcase
end

//ALU_out
always@(posedge clk)
begin
	ALU_out = ALU_result;
end

//mux3
always@(*)
begin
	if (IR[12])
		mux3 = ~(zero);
	else
		mux3 = zero;
end
	
//Mux4
always@(*)
begin
	case(PC_src)
		2'b00	:	mux4 = ALU_result;
		2'b01	:	mux4 = ALU_out;
		2'b10	:	mux4 = C;
		default	:	mux4 = 16'bx;
	endcase
end	
	
//Data Memory
always@(posedge clk)
begin
	if (mem_read)
	begin
		read_addr = ALU_out;
		MDR[7:0] = data_mem[read_addr];
		MDR[15:8] = data_mem[read_addr + 16'd1];
	end
	
	else if (mem_write)
	begin
		write_addr = ALU_out;
		write_data = B;
		data_mem[write_addr] = write_data[7:0];
		data_mem[write_addr + 16'd1] = write_data[15:8];
		$writememh("data_mem.dat",data_mem);
	end
end

//mux5
always@(*)
begin
	case(mem_to_reg)
		1'b0	:	mux5 = ALU_out;
		1'b1	:	mux5 = MDR;
	endcase
end

//Main Control Unit
always@(*)
begin
	case(stage)
		4'b0000	:	begin						
						PC_write = 1'b1;
						IR_write = 1'b1;
						ALU_src_A = 3'd0;
						ALU_src_B = 3'd0;
						PC_src = 2'd0;
						reg_write = 1'b0;
						PC_write_cond = 1'b0;
						mem_to_reg = 1'b0;
						mem_read = 1'b0;
						mem_write = 1'b0;
					end

		4'b0001	:	begin
						PC_write = 1'b0;
						IR_write = 1'b0;
						ALU_src_A = 3'd0;
						ALU_src_B = 3'd4;							
					end

		4'b0010	:	begin
						ALU_src_A = 3'd1;
						ALU_src_B = 3'd1;
					end

		4'b0011	:	begin						
						ALU_src_A = 3'd4;
						ALU_src_B = 3'd2;
					end

		4'b0100	:	begin						
						ALU_src_A = 3'd3;
						ALU_src_B = 3'd2;
					end

		4'b0101	:	begin						
						ALU_src_A = 3'd2;
						ALU_src_B = 3'd2;
					end

		4'b0110	:	begin						
						PC_src = 1'd1;
						PC_write = 1'd1;
					end

		4'b0111	:	begin						
						ALU_src_A = 3'd1;
						ALU_src_B = 3'd3;
					end

		4'b1000	:	begin	
						ALU_src_A = 3'd1;
						ALU_src_B = 3'd1;
						PC_src = 2'd2;
						PC_write_cond = 1'b1;
					end

		4'b1001	:	begin						
						reg_write = 1'b1;
					end

		4'b1010	:	begin						
						mem_read = 1'b1;
					end

		4'b1011	:	begin						
						mem_write = 1'b1;
					end					

		4'b1100	:	begin						
						reg_write = 1'b1;
						mem_to_reg = 1'b1;
						mem_read = 1'b0;
					end
		
		default	:	begin						
						IR_write = 1'bx;
						reg_write = 1'bx;
						ALU_src_A = 3'bx;
						ALU_src_B = 3'bx;
						PC_src = 2'bx;
						PC_write = 1'bx;
						PC_write_cond = 1'bx;
						mem_to_reg = 1'bx;
						mem_read = 1'bx;
						mem_write = 1'bx;
					end
	endcase
end

//Main FSM
always@(posedge clk)
begin
	case(stage)
		4'b0000	:	stage = 4'b0001;
		
		4'b0001	:	begin
						case(IR[15:12])
							4'b0000	:	stage = 4'b0011;
							4'b0001	:	stage = 4'b0111;
							4'b0010	:	stage = 4'b0111;
							4'b0011	:	stage = 4'b0110;
							4'b0100	:	stage = 4'b1000;
							4'b0101	:	stage = 4'b1000;
							4'b0110	:	stage = 4'b0101;
							4'b0111	:	stage = 4'b0101;
							4'b1000	:	stage = 4'b0010;
							4'b1001	:	stage = 4'b0101;
							4'b1010	:	stage = 4'b0100;
							4'b1011	:	stage = 4'b0010;
							4'b1100	:	stage = 4'b0010;
							4'b1101	:	stage = 4'b0101;
							4'b1110	:	stage = 4'b0100;
							4'b1111	:	stage = 4'b0010;
							default	:	stage = 4'bxxxx;
						endcase
					end
					
		4'b0010	:	stage = 4'b1001;					
		4'b0011	:	stage = 4'b1001;
		4'b0100	:	stage = 4'b1001;
		4'b0101	:	stage = 4'b1001;
		4'b0110	:	stage = 4'b0000;
		
		4'b0111	:	begin
						case(IR[15:12])
							4'b0001	:	stage = 4'b1010;
							4'b0010	:	stage = 4'b1011;
							default	:	stage = 4'bxxxx;
						endcase
					end
					
		4'b1000	:	stage = 4'b0000;
		4'b1001	:	stage = 4'b0000;
		4'b1010	:	stage = 4'b1100;
		4'b1011	:	stage = 4'b0000;
		4'b1100	:	stage = 4'b0000;
		default	:	stage = 4'bxxxx;
	endcase
end

endmodule

//************************************************************************************************************************************************************************

RISC_Processor/multi_cycle.vcd
$date
	Tue Apr 20 17:45:26 2021
$end
$version
	Icarus Verilog
$end
$timescale
	1ps
$end
$scope module tb_multi_cycle $end
$var wire 4 ! stage [3:0] $end
$var wire 1 " reg_write $end
$var wire 1 # mem_write $end
$var wire 1 $ mem_to_reg $end
$var wire 1 % mem_read $end
$var wire 1 & error_log_3 $end
$var wire 1 ' error_log_2 $end
$var wire 1 ( error_log_1 $end
$var wire 1 ) PC_write_cond $end
$var wire 1 * PC_write $end
$var wire 2 + PC_src [1:0] $end
$var wire 16 , PC [15:0] $end
$var wire 1 - IR_write $end
$var wire 3 . ALU_src_B [2:0] $end
$var wire 3 / ALU_src_A [2:0] $end
$var reg 16 0 PC_init [15:0] $end
$var reg 1 1 clk $end
$var reg 1 2 rst $end
$scope module uut $end
$var wire 16 3 PC_init [15:0] $end
$var wire 1 1 clk $end
$var wire 1 2 rst $end
$var reg 16 4 A [15:0] $end
$var reg 3 5 ALU_ctrl [2:0] $end
$var reg 16 6 ALU_out [15:0] $end
$var reg 16 7 ALU_result [15:0] $end
$var reg 3 8 ALU_src_A [2:0] $end
$var reg 3 9 ALU_src_B [2:0] $end
$var reg 16 : B [15:0] $end
$var reg 16 ; C [15:0] $end
$var reg 16 < IR [15:0] $end
$var reg 1 - IR_write $end
$var reg 16 = MDR [15:0] $end
$var reg 16 > PC [15:0] $end
$var reg 2 ? PC_src [1:0] $end
$var reg 1 * PC_write $end
$var reg 1 ) PC_write_cond $end
$var reg 1 ( error_log_1 $end
$var reg 1 ' error_log_2 $end
$var reg 1 & error_log_3 $end
$var reg 16 @ instr [15:0] $end
$var reg 1 % mem_read $end
$var reg 1 $ mem_to_reg $end
$var reg 1 # mem_write $end
$var reg 4 A mux11 [3:0] $end
$var reg 4 B mux12 [3:0] $end
$var reg 4 C mux13 [3:0] $end
$var reg 16 D mux21 [15:0] $end
$var reg 16 E mux22 [15:0] $end
$var reg 1 F mux3 $end
$var reg 16 G mux4 [15:0] $end
$var reg 16 H mux5 [15:0] $end
$var reg 4 I rdr1 [3:0] $end
$var reg 4 J rdr2 [3:0] $end
$var reg 4 K rdr3 [3:0] $end
$var reg 16 L read_addr [15:0] $end
$var reg 1 " reg_write $end
$var reg 4 M stage [3:0] $end
$var reg 16 N temp1 [15:0] $end
$var reg 16 O temp2 [15:0] $end
$var reg 16 P wd [15:0] $end
$var reg 16 Q write_addr [15:0] $end
$var reg 16 R write_data [15:0] $end
$var reg 4 S wrr [3:0] $end
$var reg 1 T zero $end
$upscope $end
$upscope $end
$enddefinitions $end
#0
$dumpvars
0T
bx S
bx R
bx Q
bx P
b10 O
b0 N
b0 M
bx L
bx K
bx J
bx I
bx H
b10 G
1F
b10 E
b0 D
b1100 C
b1100 B
b1000 A
b1000000000000 @
b0 ?
b0 >
bx =
b1000000000000 <
bx ;
bx :
b0 9
b0 8
b10 7
bx 6
b0 5
bx 4
b0 3
12
01
b0 0
b0 /
b0 .
1-
b0 ,
b0 +
1*
0)
0(
0'
0&
0%
0$
0#
0"
b0 !
$end
#2000
02
#10000
b0 O
b10 N
b0 E
b10 H
b100 .
b100 9
0-
0*
b10 D
b1010100000001 @
b0 ;
b0 :
b0 4
b1100 S
b0 K
b1100 J
b1000 I
b10 6
b1 !
b1 M
b10 ,
b10 >
11
#15000
01
#20000
0F
b0 G
1T
b0 7
b0 N
b0 D
b11 .
b11 9
b1 /
b1 8
b111 !
b111 M
11
#25000
01
#30000
b0 H
1%
b0 6
b1010 !
b1010 M
11
#35000
01
#40000
b1000100010001 H
0%
1$
1"
b1100 !
b1100 M
b1000100010001 =
b0 L
11
#45000
01
#50000
b100 G
1F
0T
b100 7
b10 O
b10 N
b1101 C
b1101 B
b1001 A
b0 H
b10 E
b10 D
b1010100000001 <
0$
0"
b0 .
b0 9
b0 /
b0 8
1-
1*
b1000100010001 P
b0 !
b0 M
11
#55000
01
#60000
b10100000001 O
b10100000101 G
b10100000001 E
b10100000101 7
b100 N
b100 .
b100 9
0-
0*
b100 H
b100 D
b1000000100001100 @
b1 !
b1 M
b100 6
b1101 S
b101 K
b1101 J
b1001 I
b100 ,
b100 >
11
#65000
01
#70000
b10 G
b10 7
b10 O
b0 N
b10 E
b0 D
b10100000101 H
b11 .
b11 9
b1 /
b1 8
b10100000101 6
b111 !
b111 M
11
#75000
01
#80000
1%
b10 H
b1010 !
b1010 M
b10 6
11
#85000
01
#90000
b10000 H
0%
1$
1"
b10000 =
b10 L
b1100 !
b1100 M
11
#95000
01
#100000
b110 G
0F
b110 7
b100 N
b1 C
b1100 B
b0 A
b10 H
b100 D
b1000000100001100 <
0$
0"
b0 .
b0 9
b0 /
b0 8
1-
1*
b0 !
b0 M
b10000 P
11
#105000
01
#110000
b100010010 G
b100010010 7
b100001100 O
b110 N
b100001100 E
b110 H
b100 .
b100 9
0-
0*
b110 D
b1010001000100010 @
b1000100010001 :
b1 S
b1 K
b1100 J
b0 I
b110 6
b1 !
b1 M
b110 ,
b110 >
11
#115000
01
#120000
b1000100010001 G
b1000100010001 7
b1000100010001 O
b0 N
b1000100010001 E
b0 D
b1 .
b1 9
b1 /
b1 8
b100010010 H
b10 !
b10 M
b100010010 6
11
#125000
01
#130000
b1000100010001 H
1"
b1000100010001 6
b1001 !
b1001 M
11
#135000
01
#140000
b1000 G
b1000 7
b10 O
b110 N
b10 C
b10 B
b10 A
b10 E
b110 D
b1010001000100010 <
0"
b0 .
b0 9
b0 /
b0 8
1-
1*
b0 !
b0 M
b1000100010001 P
11
#145000
01
#150000
b1000101010 G
b1000101010 7
b1000100010 O
b1000 N
b1000100010 E
b1000 H
b100 .
b100 9
0-
0*
b1000 D
b1001001110001000 @
b0 :
b10 S
b10 K
b10 J
b10 I
b1000 6
b1 !
b1 M
b1000 ,
b1000 >
11
#155000
01
#160000
b100010 G
b100010 7
b0 O
b100010 N
b0 E
b100010 D
b10 .
b10 9
b11 /
b11 8
b1000101010 H
b100 !
b100 M
b1000101010 6
11
#165000
01
#170000
b100010 H
1"
b100010 6
b1001 !
b1001 M
11
#175000
01
#180000
b1010 G
1F
b1010 7
b10 O
b1000 N
b11 C
b1000 B
b1000 A
b10 E
b1000 D
b1001001110001000 <
0"
b0 .
b0 9
b0 /
b0 8
1-
1*
b0 !
b0 M
b100010 P
11
#185000
01
#190000
b1110001000 O
b1110010010 G
b1110001000 E
b1110010010 7
b1010 N
b1010 H
b100 .
b100 9
0-
0*
b1010 D
b101001011000001 @
b11 S
b11 K
b1000 J
b1000 I
b1010 6
b1 !
b1 M
b1010 ,
b1010 >
11
#195000
01
#200000
b1111111110001000 G
b1111111110001000 7
b0 O
b1111111110001000 N
b0 E
b1111111110001000 D
b10 .
b10 9
b10 /
b10 8
b1110010010 H
b101 !
b101 M
b1110010010 6
11
#205000
01
#210000
b1111111110001000 H
1"
b1111111110001000 6
b1001 !
b1001 M
11
#215000
01
#220000
b1100 G
b1100 7
b10 O
b1010 N
b10 C
b1 B
b1100 A
b10 E
b1010 D
b101001011000001 <
0"
b0 .
b0 9
b0 /
b0 8
1-
1*
b0 !
b0 M
b1111111110001000 P
11
#225000
01
#230000
b1011001101 G
b1011001101 7
b1011000001 O
b1100 N
b1011000001 E
b1100 H
b100 .
b100 9
0-
0*
b1100 D
b100110111000001 @
b100010 ;
b1000100010001 :
b1000100010001 4
b10 S
b10 K
b1 J
b1100 I
b1100 6
b1 !
b1 M
b1100 ,
b1100 >
11
#235000
01
#240000
0F
1T
b1000100010001 O
b1000100010001 N
b100010 G
b1000100010001 E
b1000100010001 D
b0 7
1)
b10 +
b10 ?
b1 .
b1 9
b1 /
b1 8
b1 5
b1011001101 H
b1000 !
b1000 M
b1011001101 6
11
#245000
01
#250000
b10 O
b1100 N
b1101 C
b10 E
b1100 D
b100110111000001 <
0T
b1110 7
b0 H
b1110 G
0)
b0 +
b0 ?
b0 .
b0 9
b0 /
b0 8
1-
1*
b0 5
b0 6
b0 !
b0 M
11
#255000
01
#260000
b1111110111000001 O
b1111110111001111 G
b1111110111000001 E
b1111110111001111 7
b1110 N
b100 .
b100 9
0-
0*
b1110 H
b1110 D
b1001000000000000 @
b1 !
b1 M
b1110 6
b10000 ;
b1101 S
b1101 K
b1110 ,
b1110 >
11
#265000
01
#270000
1F
1T
b1000100010001 O
b1000100010001 N
b1000100010001 E
b1000100010001 D
b0 7
b1111110111001111 H
b10000 G
1)
b10 +
b10 ?
b1 .
b1 9
b1 /
b1 8
b1 5
b1111110111001111 6
b1000 !
b1000 M
11
#275000
01
#280000
b10 O
b10000 N
0F
b100 C
b10 B
b11 A
b10010 G
b10 E
b10000 D
0T
b10010 7
b1100010000110010 <
0)
b0 +
b0 ?
b0 .
b0 9
b0 /
b0 8
1-
1*
b0 5
b0 H
b1100010000110010 @
b0 !
b0 M
b0 6
b10000 ,
b10000 >
11
#285000
01
#290000
b10001000100 G
b10001000100 7
b10000110010 O
b10010 N
b10000110010 E
b10010 H
b100 .
b100 9
0-
0*
b10010 D
b1101001110000000 @
b0 ;
b100010 :
b1111111110001000 4
b100 S
b100 K
b10 J
b11 I
b10010 6
b1 !
b1 M
b10010 ,
b10010 >
11
#295000
01
#300000
b100010 O
b1111111110001000 N
b1111111101100110 G
b100010 E
b1111111110001000 D
b1111111101100110 7
b1 .
b1 9
b1 /
b1 8
b1 5
b10001000100 H
b10 !
b10 M
b10001000100 6
11
#305000
01
#310000
b1111111101100110 H
1"
b1111111101100110 6
b1001 !
b1001 M
11
#315000
01
#320000
1F
b10 O
b10010 N
b11 C
b0 B
b1000 A
b10100 G
b10 E
b10010 D
b1101001110000000 <
b10100 7
0"
b0 .
b0 9
b0 /
b0 8
1-
1*
b0 5
b0 !
b0 M
b1111111101100110 P
11
#325000
01
#330000
b1110010100 G
b1110010100 7
b1110000000 O
b10100 N
b1110000000 E
b10100 H
b100 .
b100 9
0-
0*
b10100 D
b1110010001100110 @
b1111111110001000 ;
b0 :
b0 4
b11 S
b11 K
b0 J
b1000 I
b10100 6
b1 !
b1 M
b10100 ,
b10100 >
11
#335000
01
#340000
b1111111110001000 O
b1111111110000000 N
b1000 G
b1111111110001000 E
b1111111110000000 D
b1000 7
b10 .
b10 9
b10 /
b10 8
b1 5
b1110010100 H
b101 !
b101 M
b1110010100 6
11
#345000
01
#350000
b1000 H
1"
b1000 6
b1001 !
b1001 M
11
#355000
01
#360000
0F
b10 O
b10100 N
b100 C
b110 B
b110 A
b10110 G
b10 E
b10100 D
b1110010001100110 <
b10110 7
0"
b0 .
b0 9
b0 /
b0 8
1-
1*
b0 5
b0 !
b0 M
b1000 P
11
#365000
01
#370000
b10001111100 G
b10001111100 7
b10001100110 O
b10110 N
b10001100110 E
b10110 H
b100 .
b100 9
0-
0*
b10110 D
b1011010100010010 @
b1111111101100110 ;
b100 S
b100 K
b110 J
b110 I
b10110 6
b1 !
b1 M
b10110 ,
b10110 >
11
#375000
01
#380000
b1111111101100110 O
b1100110 N
b1111111100000000 G
b1111111101100110 E
b1100110 D
b1111111100000000 7
b10 .
b10 9
b11 /
b11 8
b1 5
b10001111100 H
b100 !
b100 M
b10001111100 6
11
#385000
01
#390000
b1111111100000000 H
1"
b1111111100000000 6
b1001 !
b1001 M
11
#395000
01
#400000
1F
b10 O
b10110 N
b101 C
b10 B
b1 A
b11000 G
b10 E
b10110 D
b1011010100010010 <
b11000 7
0"
b0 .
b0 9
b0 /
b0 8
1-
1*
b0 5
b0 !
b0 M
b1111111100000000 P
11
#405000
01
#410000
b10100101010 G
b10100101010 7
b10100010010 O
b11000 N
b10100010010 E
b11000 H
b100 .
b100 9
0-
0*
b11000 D
b1111011000110010 @
b0 ;
b100010 :
b1000100010001 4
b101 S
b101 K
b10 J
b1 I
b11000 6
b1 !
b1 M
b11000 ,
b11000 >
11
#415000
01
#420000
b100010 O
b1000100010001 N
b1111111111111111 G
b100010 E
b1000100010001 D
b1111111111111111 7
b1 .
b1 9
b1 /
b1 8
b10 5
b10100101010 H
b10 !
b10 M
b10100101010 6
11
#425000
01
#430000
b1111111111111111 H
1"
b1111111111111111 6
b1001 !
b1001 M
11
#435000
01
#440000
b10 O
b11000 N
b110 C
b11 A
b11010 G
b10 E
b11000 D
b1111011000110010 <
b11010 7
0"
b0 .
b0 9
b0 /
b0 8
1-
1*
b0 5
b0 !
b0 M
b1111111111111111 P
11
#445000
01
#450000
b11000110010 O
b11001001100 G
b11000110010 E
b11001001100 7
b11010 N
b11010 H
b100 .
b100 9
0-
0*
b11010 D
b111010001110111 @
b1000 4
b110 S
b110 K
b11 I
b11010 6
b1 !
b1 M
b11010 ,
b11010 >
11
#455000
01
#460000
b100010 O
b1000 N
b101010 G
b100010 E
b1000 D
b101010 7
b1 .
b1 9
b1 /
b1 8
b11 5
b11001001100 H
b10 !
b10 M
b11001001100 6
11
#465000
01
#470000
b101010 H
1"
b101010 6
b1001 !
b1001 M
11
#475000
01
#480000
b11100 G
b11100 7
b10 O
b11010 N
b100 C
b111 B
b111 A
b10 E
b11010 D
b111010001110111 <
0"
b0 .
b0 9
b0 /
b0 8
1-
1*
b0 5
b0 !
b0 M
b101010 P
11
#485000
01
#490000
b10010010011 G
b10010010011 7
b10001110111 O
b11100 N
b10001110111 E
b11100 H
b100 .
b100 9
0-
0*
b11100 D
b110110010101010 @
b1111111100000000 ;
b0 :
b0 4
b100 S
b100 K
b111 J
b111 I
b11100 6
b1 !
b1 M
b11100 ,
b11100 >
11
#495000
01
#500000
b1111111100000000 O
b1110111 N
b1111111111111111 G
b1111111100000000 E
b1110111 D
b1111111111111111 7
b10 .
b10 9
b10 /
b10 8
b10 5
b10010010011 H
b101 !
b101 M
b10010010011 6
11
