Labtest/labtest.v
// Tanvi Shewale 2018A3PS0298P
// Abhinandan Sharma 2018A3PS0095P

module division (FLAG, qnt, rem, inA, inB, CLOCK, RESET, LOAD);

input CLOCK, RESET, LOAD ;
input [15:0]inA ;
input [7:0]inB;
output reg [2:0] FLAG;
output reg [15:0] qnt; 
output reg [7:0]rem; 

wire spcase1, spcase2,spcase3,spcase4,spcase5;
reg [15:0] count;
reg [15:0] diff;

assign spcase1 = ~|inB;
assign spcase2 = ~(~inB[0] | inB[1] | inB[2] | inB[3] | inB[4] | inB[5] | inB[6] | inB[7]);
assign spcase3 = ~((inB[0] | ~inB[1] | inB[2] | inB[3] | inB[4] | inB[5] | inB[6] | inB[7] ) &
				   (inB[0] | inB[1] | ~inB[2] | inB[3] | inB[4] | inB[5] | inB[6] | inB[7] ) &
				   (inB[0] | inB[1] | inB[2] | ~inB[3] | inB[4] | inB[5] | inB[6] | inB[7] ) &
				   (inB[0] | inB[1] | inB[2] | inB[3] | ~inB[4] | inB[5] | inB[6] | inB[7] ) &
				   (inB[0] | inB[1] | inB[2] | inB[3] | inB[4] | ~inB[5] | inB[6] | inB[7] ) &
				   (inB[0] | inB[1] | inB[2] | inB[3] | inB[4] | inB[5] | ~inB[6] | inB[7] ) &
				   (inB[0] | inB[1] | inB[2] | inB[3] | inB[4] | inB[5] | inB[6] | ~inB[7] ) ) &
				   (~spcase5);
				   				  
assign spcase4 = ~(((|(inA[15:8] ^ inB )) | inA[7] | inA[6] | inA[5] | inA[4] | inA[3] | inA[2] | inA[1] | inA[0]) &	
                    (inA[15] | (|(inA[14:7] ^ inB )) | inA[6] | inA[5] | inA[4] | inA[3] | inA[2] | inA[1] | inA[0]) &				  
		            (inA[15] | inA[14] | (|(inA[13:6] ^ inB )) | inA[5] | inA[4] | inA[3] | inA[2] | inA[1] | inA[0]) &
					(inA[15] | inA[14] | inA[13] | (|(inA[12:5] ^ inB )) | inA[4] | inA[3] | inA[2] | inA[1] | inA[0]) &
					(inA[15] | inA[14] | inA[13] | inA[12] | (|(inA[11:4] ^ inB )) | inA[3] | inA[2] | inA[1] | inA[0]) &
					(inA[15] | inA[14] | inA[13] | inA[12] | inA[11] | (|(inA[10:3] ^ inB )) | inA[2] | inA[1] | inA[0]) &
					(inA[15] | inA[14] | inA[13] | inA[12] | inA[11]  | inA[10] | (|(inA[9:2] ^ inB )) | inA[1] | inA[0]) &
					(inA[15] | inA[14] | inA[13] | inA[12] | inA[11]  | inA[10] | inA[9] | (|(inA[8:1] ^ inB )) | inA[0])) &
//					(inA[15] | inA[14] | inA[13] | inA[12] | inA[11]  | inA[10] | inA[9] | inA[8] | (|(inA[7:0] ^ inB )))) & 
					(~spcase1) &
					(~spcase2);
					
assign spcase5 = ((inA[7:0] < {8'd0, inB})	? 1'b1 : 1'b0) & ~spcase2;	

always @ (RESET, posedge CLOCK)
begin
	if(RESET == 1'b1)
		begin
			FLAG = 3'b000; 
			rem = 8'd0;
			qnt = 16'd0;
		end
		
	else  
	begin
		case ({spcase1, spcase2, spcase3, spcase4, spcase5})
			5'b10000	:	begin 
								qnt = 16'b11111111_11111111;
								rem = 8'b11111111;
								FLAG = 3'b011;
							end
			5'b01000	:	begin
								qnt = inA;
								rem = 8'd0;
								FLAG = 3'b100;
							end
			5'b00100	:	begin
								if (inB == 8'b10000000)
								begin
									qnt <= {7'd0, inA[15:7]};
									rem <= {1'd0, inA[6:0]};
								end
								else if (inB == 8'b01000000)
								begin
									qnt <= {6'd0, inA[15:6]};
									rem <= {2'd0, inA[5:0]};
								end
								else if (inB == 8'b00100000)
								begin
									qnt <= {5'd0, inA[15:5]};
									rem <= {3'd0, inA[4:0]};
								end
								else if (inB == 8'b00010000)
								begin
									qnt <= {4'd0, inA[15:4]};
									rem <= {4'd0, inA[3:0]};
								end
								else if (inB == 8'b00001000)
								begin
									qnt <= {3'd0, inA[15:3]};
									rem <= {5'd0, inA[2:0]};
								end
								else if (inB == 8'b00000100)
								begin
									qnt <= {2'd0, inA[15:2]};
									rem <= {6'd0, inA[1:0]};
								end
								else if (inB == 8'b00000010)
								begin
									qnt <= {1'b0, inA[15:1]};
									rem <= {7'd0, inA[0]};
								end
								// else
								// begin
									// qnt <= 16'dz;
									// rem <= 8'dz;
								// end

								FLAG = 3'b101;	
							end
			5'b00010   :	begin 
								if (~((|(inA[15:8] ^ inB )) | inA[7] | inA[6] | inA[5] | inA[4] | inA[3] | inA[2] | inA[1] | inA[0]))
									qnt <= 16'b00000001_00000000;
								else if (~(inA[15] | (|(inA[14:7] ^ inB )) | inA[6] | inA[5] | inA[4] | inA[3] | inA[2] | inA[1] | inA[0]))
									qnt <= 16'b00000000_10000000;
								else if (~(inA[15] | inA[14] | (|(inA[13:6] ^ inB )) | inA[5] | inA[4] | inA[3] | inA[2] | inA[1] | inA[0]))	
									qnt <= 16'b00000000_01000000;
								else if (~(inA[15] | inA[14] | inA[13] | (|(inA[12:5] ^ inB )) | inA[4] | inA[3] | inA[2] | inA[1] | inA[0]))
									qnt <= 16'b00000000_00100000;
								else if (~(inA[15] | inA[14] | inA[13] | inA[12] | (|(inA[11:4] ^ inB )) | inA[3] | inA[2] | inA[1] | inA[0]))
									qnt <= 16'b00000000_00010000;
								else if (~(inA[15] | inA[14] | inA[13] | inA[12] | inA[11] | (|(inA[10:3] ^ inB )) | inA[2] | inA[1] | inA[0]))
									qnt <= 16'b00000000_00001000;
								else if (~(inA[15] | inA[14] | inA[13] | inA[12] | inA[11]  | inA[10] | (|(inA[9:2] ^ inB )) | inA[1] | inA[0]))
									qnt <= 16'b00000000_00000100;
								else if (~(inA[15] | inA[14] | inA[13] | inA[12] | inA[11]  | inA[10] | inA[9] | (|(inA[8:1] ^ inB )) | inA[0]))	
									qnt <= 16'b00000000_00000010;
								else if (~(inA[15] | inA[14] | inA[13] | inA[12] | inA[11]  | inA[10] | inA[9] | inA[8] | (|(inA[7:0] ^ inB ))))
									qnt <= 16'b00000000_00000001;
								// else 
									// qnt <= 16'dz;
								rem <= 8'b0;
								FLAG <= 3'b110;
							end	
			5'b00001	:	begin
								qnt = 16'd0;
								rem = inA[7:0];
								FLAG = 3'b111;
							end
			5'b00000	:	begin
								FLAG = 3'b001;
								diff = diff - {8'd0,inB};
								count = count + 16'd1;
								if (diff < inB)
								begin 
									qnt = count;
									rem = diff;
									FLAG = 3'b010;
								end
							end
			default 	:	begin 
								qnt = 16'dz;
								rem = 8'dz;
								FLAG = 3'dz;
							end	
		endcase
	end	
end	

always @(posedge CLOCK)
begin
	if(LOAD == 1'b1)
	begin
		diff = inA;
		count = 16'd0;		
	end
end			

endmodule

/*************************************************************************************************************************************/

module tb_division();

reg CLOCK, RESET, LOAD ;
reg [15:0] inA;
reg [7:0] inB;
wire [2:0] FLAG;
wire [15:0] qnt;
wire [7:0] rem;


division uut (FLAG, qnt, rem, inA, inB, CLOCK, RESET, LOAD);

initial 
begin
CLOCK = 1'b1;	
end

always #5 CLOCK = ~CLOCK;

initial 
begin
	$monitor ("inA = %b	inB = %b	RESET = %b	LOAD = %b	qnt = %b	rem = %b	FLAG = %b", inA, inB, RESET, LOAD, qnt, rem, FLAG);
	$dumpfile("division.vcd");
	$dumpvars(0,tb_division);
	
	RESET = 1'b1;
	#10
	RESET = 1'b0;
	inA = 16'd10;
	inB = 8'd0;
	LOAD = 1'b1;
	#25
	LOAD = 1'b0;
	#15
	inA = 16'd10;
	inB = 8'd1;
	LOAD = 1'b1;
	#25
	LOAD = 1'b0;
	#15
	inA = 16'd10;
	inB = 8'd8;
	LOAD = 1'b1;
	#25
	LOAD = 1'b0;
	#15
	inA = 16'b00000111_11000000;
	inB = 8'b00111110;
	LOAD = 1'b1;
	#25
	LOAD = 1'b0;
	#15
	inA = 16'd9;
	inB = 8'd15;
	LOAD = 1'b1;
	#25
	LOAD = 1'b0;
	#15
	inA = 16'd50;
	inB = 8'd50;
	LOAD = 1'b1;
	#25
	LOAD = 1'b0;
	#15
	// inA = 16'b11111111_11111111;
	// inB = 8'd3;
	// LOAD = 1'b1;
	// #25
	// LOAD = 1'b0;
	// #437000
	inA = 16'd50;
	inB = 8'd21;
	LOAD = 1'b1;
	#25	
	LOAD = 1'b0;
	#15
	inA = 16'd250;
	inB = 8'd17;
	LOAD = 1'b1;
	#15
	LOAD = 1'b0;
	#150
	$finish;
	
end
endmodule

Labtest/division.vcd
$date
	Mon Nov 29 22:56:55 2021
$end
$version
	Icarus Verilog
$end
$timescale
	1s
$end
$scope module tb_division $end
$var wire 8 ! rem [7:0] $end
$var wire 16 " qnt [15:0] $end
$var wire 3 # FLAG [2:0] $end
$var reg 1 $ CLOCK $end
$var reg 1 % LOAD $end
$var reg 1 & RESET $end
$var reg 16 ' inA [15:0] $end
$var reg 8 ( inB [7:0] $end
$scope module uut $end
$var wire 1 $ CLOCK $end
$var wire 1 % LOAD $end
$var wire 1 & RESET $end
$var wire 16 ) inA [15:0] $end
$var wire 8 * inB [7:0] $end
$var wire 1 + spcase2 $end
$var wire 1 , spcase3 $end
$var wire 1 - spcase4 $end
$var wire 1 . spcase5 $end
$var wire 1 / spcase1 $end
$var reg 3 0 FLAG [2:0] $end
$var reg 16 1 count [15:0] $end
$var reg 16 2 diff [15:0] $end
$var reg 16 3 qnt [15:0] $end
$var reg 8 4 rem [7:0] $end
$upscope $end
$upscope $end
$enddefinitions $end
#0
$dumpvars
b0 4
b0 3
bx 2
bx 1
b0 0
x/
x.
x-
x,
x+
bx *
bx )
bx (
bx '
1&
x%
1$
b0 #
b0 "
b0 !
$end
#5
0$
#10
0,
0+
0-
0.
b0 1
b1010 2
bz #
bz 0
bz !
bz 4
bz "
bz 3
1$
1%
1/
b0 (
b0 *
b1010 '
b1010 )
0&
#15
0$
#20
b11 #
b11 0
b11111111 !
b11111111 4
b1111111111111111 "
b1111111111111111 3
1$
#25
0$
#30
1$
#35
0$
0%
#40
1$
#45
0$
#50
1+
b0 1
b1010 2
b1 #
b1 0
1$
1%
0/
b1 (
b1 *
#55
0$
#60
b100 #
b100 0
b0 !
b0 4
b1010 "
b1010 3
1$
#65
0$
#70
1$
#75
0$
0%
#80
1$
#85
0$
#90
1,
0+
1$
1%
b1000 (
b1000 *
#95
0$
#100
b10 !
b10 4
b1 "
b1 3
b101 #
b101 0
1$
#105
0$
#110
1$
#115
0$
0%
#120
1$
#125
0$
#130
1-
0,
b11111000000 2
1$
1%
b111110 (
b111110 *
b11111000000 '
b11111000000 )
#135
0$
#140
b110 #
b110 0
b0 !
b0 4
b100000 "
b100000 3
1$
#145
0$
#150
1$
#155
0$
0%
#160
1$
#165
0$
#170
0-
1.
b1001 2
1$
1%
b1111 (
b1111 *
b1001 '
b1001 )
#175
0$
#180
b111 #
b111 0
b1001 !
b1001 4
b0 "
b0 3
1$
#185
0$
#190
1$
#195
0$
0%
#200
1$
#205
0$
#210
0.
b110010 2
b110010 !
b110010 4
1$
1%
b110010 (
b110010 *
b110010 '
b110010 )
#215
0$
#220
b0 !
b0 4
b1 "
b1 3
b0 1
b110010 2
b10 #
b10 0
1$
#225
0$
#230
b0 1
b110010 2
b10 #
b10 0
1$
#235
0$
0%
#240
b1 1
b0 2
b10 #
b10 0
1$
#245
0$
#250
b0 1
b110010 2
b1 #
b1 0
1$
1%
b10101 (
b10101 *
#255
0$
#260
b0 1
b110010 2
1$
#265
0$
#270
b0 1
b110010 2
1$
#275
0$
0%
#280
b1 1
b11101 2
1$
#285
0$
#290
b10 #
b10 0
b1100 !
b1100 4
b10 "
b10 3
b0 1
b11111010 2
1$
1%
b10001 (
b10001 *
b11111010 '
b11111010 )
#295
0$
#300
b0 1
b11111010 2
b1 #
b1 0
1$
#305
0$
0%
#310
b1 1
b11101001 2
1$
#315
0$
#320
b10 1
b11011000 2
1$
#325
0$
#330
b11 1
b11000111 2
1$
#335
0$
#340
b100 1
b10110110 2
1$
#345
0$
#350
b101 1
b10100101 2
1$
#355
0$
#360
b110 1
b10010100 2
1$
#365
0$
#370
b111 1
b10000011 2
1$
#375
0$
#380
b1000 1
b1110010 2
1$
#385
0$
#390
b1001 1
b1100001 2
1$
#395
0$
#400
b1010 1
b1010000 2
1$
#405
0$
#410
b1011 1
b111111 2
1$
#415
0$
#420
b1100 1
b101110 2
1$
#425
0$
#430
b1101 1
b11101 2
1$
#435
0$
#440
b10 #
b10 0
b1110 "
b1110 3
b1110 1
b1100 2
1$
#445
0$
#450
b1111 1
b1111111111111011 2
b1 #
b1 0
1$
