Lab5/mult_p_ref.v
`timescale 1ns/1ns

module pipeline(A,B,op,clk,rst);

input [7:0] A;
input [7:0] B;
input clk;
input rst;
output reg [15:0] op;

reg [7:0] A0;
reg [7:0] A1;
reg [7:0] A2;
reg [7:0] A3;

reg [7:0] B0;
reg [7:0] B1;
reg [7:0] B2;
reg [7:0] B3;

reg [7:0] M0;
reg [7:0] M1;
reg [7:0] M2;
reg [7:0] M3;

reg [15:0] S0;
reg [15:0] S1;
reg [15:0] S2;
reg [15:0] S3;

always @ (posedge clk) begin
if (rst == 1)
op = 16'b0000000000000000;
else begin
	fork
	begin
	A0 = A;
	B0 = B;
	M0 = A[3:0] * B[3:0];
	S0 = {8'b00000000,M0};
	end
	
	begin
	#1
	A1 = A0;
	B1 = B0;
	M1 = A[3:0] * B[7:4];
	S1 = S0 + {4'b0000,M1,4'b0000};
	end
	
	begin
	#2
	A2 = A1;
	B2 = B1;
	M2 = A[7:4] * B[3:0];
	S2 = S1 + {4'b0000,M2,4'b0000};
	end
	
	begin
	#3
	A3 = A2;
	B3 = B2;
	M3 = A[7:4] * B[7:4];
	S3 = S2 + {M3,8'b00000000};
	end
	join
	
	op = S3;
	end
end
endmodule
	


module tb_pipeline();
reg clk, rst;
reg [7:0] A;
reg [7:0] B;
wire [15:0] op;

pipeline uut (.clk(clk), .rst(rst), .A(A), .B(B), .op(op));


initial begin
clk = 1'b0;
rst = 1'b1;
end

always #200 clk = ~clk;

initial begin
$dumpfile("pipeline.vcd");
$dumpvars(0);
rst = 1'b0;
A = 8'b00000100;
B = 8'b00010001;
$display($time,"	A = %d	B = %d	op = %d", A, B, op);
#400
A = 8'b11000100;
B = 8'b10010011;
$display($time,"	A = %d	B = %d	op = %d", A, B, op);
#400
A = 8'b00000010;
B = 8'b10000111;
$display($time,"	A = %d	B = %d	op = %d", A, B, op);
#400
A = 8'b00000010;
B = 8'b00000011;
$display($time,"	A = %d	B = %d	op = %d", A, B, op);
#400
A = 8'b11111111;
B = 8'b00000011;
$display($time,"	A = %d	B = %d	op = %d", A, B, op);

$finish;
end

endmodule

Lab5/pipeline.vcd
$date
	Mon Mar 29 23:22:48 2021
$end
$version
	Icarus Verilog
$end
$timescale
	1ns
$end
$scope module tb_pipeline $end
$var wire 16 ! op [15:0] $end
$var reg 8 " A [7:0] $end
$var reg 8 # B [7:0] $end
$var reg 1 $ clk $end
$var reg 1 % rst $end
$scope module uut $end
$var wire 8 & A [7:0] $end
$var wire 8 ' B [7:0] $end
$var wire 1 $ clk $end
$var wire 1 % rst $end
$var reg 8 ( A0 [7:0] $end
$var reg 8 ) A1 [7:0] $end
$var reg 8 * A2 [7:0] $end
$var reg 8 + A3 [7:0] $end
$var reg 8 , B0 [7:0] $end
$var reg 8 - B1 [7:0] $end
$var reg 8 . B2 [7:0] $end
$var reg 8 / B3 [7:0] $end
$var reg 8 0 M0 [7:0] $end
$var reg 8 1 M1 [7:0] $end
$var reg 8 2 M2 [7:0] $end
$var reg 8 3 M3 [7:0] $end
$var reg 16 4 S0 [15:0] $end
$var reg 16 5 S1 [15:0] $end
$var reg 16 6 S2 [15:0] $end
$var reg 16 7 S3 [15:0] $end
$var reg 16 8 op [15:0] $end
$upscope $end
$upscope $end
$enddefinitions $end
#0
$dumpvars
bx 8
bx 7
bx 6
bx 5
bx 4
bx 3
bx 2
bx 1
bx 0
bx /
bx .
bx -
bx ,
bx +
bx *
bx )
bx (
b10001 '
b100 &
0%
0$
b10001 #
b100 "
bx !
$end
#200
b100 4
b100 0
b10001 ,
b100 (
1$
#201
b1000100 5
b100 1
b10001 -
b100 )
#202
b1000100 6
b0 2
b10001 .
b100 *
#203
b1000100 !
b1000100 8
b1000100 7
b0 3
b10001 /
b100 +
#400
0$
b10010011 #
b10010011 '
b11000100 "
b11000100 &
#600
b1100 4
b1100 0
b10010011 ,
b11000100 (
1$
#601
b1001001100 5
b100100 1
b10010011 -
b11000100 )
#602
b10010001100 6
b100100 2
b10010011 .
b11000100 *
#603
b111000010001100 !
b111000010001100 8
b111000010001100 7
b1101100 3
b10010011 /
b11000100 +
#800
0$
b10000111 #
b10000111 '
b10 "
b10 &
#1000
b1110 4
b1110 0
b10000111 ,
b10 (
1$
#1001
b100001110 5
b10000 1
b10000111 -
b10 )
#1002
b100001110 6
b0 2
b10000111 .
b10 *
#1003
b100001110 !
b100001110 8
b100001110 7
b0 3
b10000111 /
b10 +
#1200
0$
b11 #
b11 '
#1400
b110 4
b110 0
b11 ,
1$
#1401
b110 5
b0 1
b11 -
#1402
b110 6
b11 .
#1403
b110 !
b110 8
b110 7
b11 /
#1600
0$
b11111111 "
b11111111 &
#1800
b101101 4
b101101 0
b11111111 (
1$
#1801
b101101 5
b11111111 )
#1802
b1011111101 6
b101101 2
b11111111 *
#1803
b1011111101 !
b1011111101 8
b1011111101 7
b11111111 +
